{"control": {"sendMessage": [{"onMessage": [[{"id": "34zJbigM", "inletIndex": 0}]], "id": "64WB82kK"}, {"onMessage": [[{"id": "1oarSilj", "inletIndex": 1}], []], "id": "Np2A0Hma"}, {"onMessage": [[{"id": "64WB82kK", "inletIndex": 0}]], "id": "MLl5jsqt"}, {"onMessage": [[{"id": "Np2A0Hma", "inletIndex": 0}], [{"id": "1oarSilj", "inletIndex": 0}]], "id": "MKJjn0Sx"}, {"onMessage": [[{"id": "MLl5jsqt", "inletIndex": 0}]], "id": "1oarSilj"}, {"onMessage": [[{"id": "aut8Yt4Y", "inletIndex": 0}]], "id": "34zJbigM"}, {"onMessage": [[{"id": "rM26PKT8", "inletIndex": 0}]], "id": "bnsRVnsp"}, {"onMessage": [[{"id": "X3fUcOw4", "inletIndex": 0}], [{"id": "hDGCqg3z", "inletIndex": 0}]], "id": "16KBbHuy"}, {"onMessage": [[{"id": "BX2BM73a", "inletIndex": 0}]], "id": "hDGCqg3z"}, {"onMessage": [[{"id": "bnsRVnsp", "inletIndex": 0}]], "id": "BX2BM73a"}, {"onMessage": [[{"id": "hDGCqg3z", "inletIndex": 1}], []], "id": "X3fUcOw4"}, {"onMessage": [[{"id": "VtfBrZPE", "inletIndex": 0}]], "id": "rM26PKT8"}, {"onMessage": [[{"id": "zj7mX5Zl", "inletIndex": 0}]], "id": "TyPLDmk3"}, {"onMessage": [[{"id": "khAFsJvr", "inletIndex": 0}], [{"id": "dHjPAE2h", "inletIndex": 0}]], "id": "ym65bbOa"}, {"onMessage": [[{"id": "TyPLDmk3", "inletIndex": 0}]], "id": "dHjPAE2h"}, {"onMessage": [[{"id": "dHjPAE2h", "inletIndex": 1}], []], "id": "khAFsJvr"}, {"onMessage": [[{"id": "uKqsmIC7", "inletIndex": 0}]], "id": "zj7mX5Zl"}, {"onMessage": [[{"id": "awkwSxvB", "inletIndex": 0}]], "id": "uKqsmIC7"}, {"onMessage": [[{"id": "ym65bbOa", "inletIndex": 0}, {"id": "16KBbHuy", "inletIndex": 0}, {"id": "MKJjn0Sx", "inletIndex": 0}, {"id": "9Nry2y47", "inletIndex": 0}, {"id": "wuJ2UxHJ", "inletIndex": 0}, {"id": "C4FFxZsY", "inletIndex": 0}, {"id": "04GU2JcG", "inletIndex": 0}, {"id": "USsAkyex", "inletIndex": 0}, {"id": "PFjA3kUE", "inletIndex": 0}, {"id": "rGxV73Sc", "inletIndex": 0}, {"id": "36iLMAXw", "inletIndex": 0}, {"id": "XmHhEsRF", "inletIndex": 0}, {"id": "WM44L5Vk", "inletIndex": 0}, {"id": "qsp8fJ3r", "inletIndex": 0}, {"id": "NHJrrzJX", "inletIndex": 0}, {"id": "PZqNkw5L", "inletIndex": 0}, {"id": "iwdWSRnX", "inletIndex": 0}, {"id": "sV29vKkJ", "inletIndex": 0}, {"id": "PN6P17Jp", "inletIndex": 0}, {"id": "7H4n2H8V", "inletIndex": 0}, {"id": "XE6cLVzR", "inletIndex": 0}]], "id": "mrqNjPCT"}, {"onMessage": [[{"id": "ltK4iqoa", "inletIndex": 0}]], "id": "iwdWSRnX"}, {"onMessage": [[{"id": "XID8sJpX", "inletIndex": 1}]], "id": "ltK4iqoa"}, {"onMessage": [[{"id": "bKtq7nSs", "inletIndex": 0}]], "id": "duj9Vzsa"}, {"onMessage": [[{"id": "8veCtKn3", "inletIndex": 0}]], "id": "sV29vKkJ"}, {"onMessage": [[{"id": "sXHFfO3Q", "inletIndex": 5}]], "id": "YgJ9XK9f"}, {"onMessage": [[{"id": "YgJ9XK9f", "inletIndex": 0}]], "id": "B8xxMvcW"}, {"onMessage": [[{"id": "SunTPbc3", "inletIndex": 0}]], "id": "PZqNkw5L"}, {"onMessage": [[{"id": "GWKn0ZtA", "inletIndex": 0}, {"id": "duj9Vzsa", "inletIndex": 0}, {"id": "5sgegJNE", "inletIndex": 0}]], "id": "aqPsZuvz"}, {"onMessage": [[{"id": "5sgegJNE", "inletIndex": 1}, {"id": "oGrt12K5", "inletIndex": 0}, {"id": "xawwm4se", "inletIndex": 0}]], "id": "XID8sJpX"}, {"onMessage": [[{"id": "XID8sJpX", "inletIndex": 0}]], "id": "8veCtKn3"}, {"onMessage": [[{"id": "5sUnBs4A", "inletIndex": 1}]], "id": "GHgiPdmQ"}, {"onMessage": [[{"id": "sXHFfO3Q", "inletIndex": 4}]], "id": "bKtq7nSs"}, {"onMessage": [[{"id": "1gij5Yvz", "inletIndex": 0}, {"id": "GHgiPdmQ", "inletIndex": 0}, {"id": "hwFdDnOR", "inletIndex": 0}]], "id": "QDP4a1fs"}, {"onMessage": [[{"id": "QDP4a1fs", "inletIndex": 0}]], "id": "xawwm4se"}, {"onMessage": [[{"id": "xawwm4se", "inletIndex": 1}]], "id": "SunTPbc3"}, {"onMessage": [[{"id": "5sUnBs4A", "inletIndex": 0}]], "id": "hwFdDnOR"}, {"onMessage": [[{"id": "GHgiPdmQ", "inletIndex": 1}]], "id": "5sgegJNE"}, {"onMessage": [[{"id": "DALXMOTs", "inletIndex": 0}]], "id": "oGrt12K5"}, {"onMessage": [[{"id": "B8xxMvcW", "inletIndex": 0}]], "id": "GWKn0ZtA"}, {"onMessage": [[{"id": "sV29vKkJ", "inletIndex": 0}]], "id": "4UTMJI96"}, {"onMessage": [[{"id": "duj9Vzsa", "inletIndex": 1}]], "id": "DALXMOTs"}, {"onMessage": [[{"id": "sXHFfO3Q", "inletIndex": 1}]], "id": "5sUnBs4A"}, {"onMessage": [[{"id": "aqPsZuvz", "inletIndex": 0}]], "id": "1gij5Yvz"}, {"onMessage": [[{"id": "rGxV73Sc", "inletIndex": 0}, {"id": "3d6iVWIq", "inletIndex": 0}, {"id": "PN6P17Jp", "inletIndex": 0}, {"id": "Hn7QnS1j", "inletIndex": 0}]], "id": "RKuXHjLd"}, {"onMessage": [[{"id": "Jj3x8zHW", "inletIndex": 1}]], "id": "OH7InqxW"}, {"onMessage": [[{"id": "dkJfqr6y", "inletIndex": 0}]], "id": "7H4n2H8V"}, {"onMessage": [[{"id": "cX4wdgmP", "inletIndex": 1}]], "id": "dkJfqr6y"}, {"onMessage": [[{"id": "zxhx5cMP", "inletIndex": 1}]], "id": "OQc4Eh31"}, {"onMessage": [[{"id": "OH7InqxW", "inletIndex": 0}]], "id": "PN6P17Jp"}, {"onMessage": [[{"id": "tar7c5jV", "inletIndex": 4}]], "id": "3lyQUVNV"}, {"onMessage": [[{"id": "HyJtdoqi", "inletIndex": 0}]], "id": "asjgeXP8"}, {"onMessage": [[{"id": "OQc4Eh31", "inletIndex": 0}]], "id": "Gsokg6Wm"}, {"onMessage": [[{"id": "HyJtdoqi", "inletIndex": 1}]], "id": "MId9blJb"}, {"onMessage": [[{"id": "XE6cLVzR", "inletIndex": 0}]], "id": "Hn7QnS1j"}, {"onMessage": [[{"id": "cX4wdgmP", "inletIndex": 0}]], "id": "BVwUKxZs"}, {"onMessage": [[{"id": "UgMUMfMq", "inletIndex": 0}]], "id": "RVgL7XKy"}, {"onMessage": [[{"id": "MId9blJb", "inletIndex": 1}]], "id": "MAzG1OpX"}, {"onMessage": [[{"id": "tar7c5jV", "inletIndex": 5}]], "id": "UgMUMfMq"}, {"onMessage": [[{"id": "r2qEYE1k", "inletIndex": 0}, {"id": "zxhx5cMP", "inletIndex": 0}, {"id": "MAzG1OpX", "inletIndex": 0}]], "id": "DBzrryKD"}, {"onMessage": [[{"id": "DBzrryKD", "inletIndex": 0}]], "id": "pmAvZCLv"}, {"onMessage": [[{"id": "tar7c5jV", "inletIndex": 1}]], "id": "HyJtdoqi"}, {"onMessage": [[{"id": "MAzG1OpX", "inletIndex": 1}, {"id": "Gsokg6Wm", "inletIndex": 0}, {"id": "Jj3x8zHW", "inletIndex": 0}]], "id": "cX4wdgmP"}, {"onMessage": [[{"id": "WfaAKmnL", "inletIndex": 0}]], "id": "Jj3x8zHW"}, {"onMessage": [[{"id": "RVgL7XKy", "inletIndex": 0}]], "id": "r2qEYE1k"}, {"onMessage": [[{"id": "BVwUKxZs", "inletIndex": 0}]], "id": "XE6cLVzR"}, {"onMessage": [[{"id": "3lyQUVNV", "inletIndex": 0}]], "id": "zxhx5cMP"}, {"onMessage": [[{"id": "pmAvZCLv", "inletIndex": 0}, {"id": "MId9blJb", "inletIndex": 0}, {"id": "asjgeXP8", "inletIndex": 0}]], "id": "WfaAKmnL"}, {"onMessage": [[{"id": "scDLNTaT", "inletIndex": 0}, {"id": "08BLB4hJ", "inletIndex": 0}, {"id": "RKuXHjLd", "inletIndex": 0}]], "id": "2EnZ9wzD"}, {"onMessage": [[{"id": "jI3nRZ3I", "inletIndex": 5}]], "id": "UZ7DgDsX"}, {"onMessage": [[{"id": "0EtPiUGl", "inletIndex": 1}, {"id": "LFLmCJ1Q", "inletIndex": 0}, {"id": "N5Z37uK9", "inletIndex": 0}]], "id": "KIu4tBtN"}, {"onMessage": [[{"id": "wFc3LBVU", "inletIndex": 1}]], "id": "9UaI8X94"}, {"onMessage": [[{"id": "ufgWJbPN", "inletIndex": 0}, {"id": "9UaI8X94", "inletIndex": 0}, {"id": "u19ClEKl", "inletIndex": 0}]], "id": "GeTZbG9G"}, {"onMessage": [[{"id": "N5Z37uK9", "inletIndex": 1}]], "id": "91Q3Vlm5"}, {"onMessage": [[{"id": "KIu4tBtN", "inletIndex": 0}]], "id": "R1lQlkKU"}, {"onMessage": [[{"id": "jI3nRZ3I", "inletIndex": 4}]], "id": "Wxpz8xdG"}, {"onMessage": [[{"id": "jI3nRZ3I", "inletIndex": 1}]], "id": "wFc3LBVU"}, {"onMessage": [[{"id": "wFc3LBVU", "inletIndex": 0}]], "id": "u19ClEKl"}, {"onMessage": [[{"id": "wdXg9sSu", "inletIndex": 0}]], "id": "ufgWJbPN"}, {"onMessage": [[{"id": "9UaI8X94", "inletIndex": 1}]], "id": "0EtPiUGl"}, {"onMessage": [[{"id": "UZ7DgDsX", "inletIndex": 0}]], "id": "ZDPEjJI5"}, {"onMessage": [[{"id": "R1lQlkKU", "inletIndex": 0}]], "id": "PFjA3kUE"}, {"onMessage": [[{"id": "ZDPEjJI5", "inletIndex": 0}]], "id": "j6raFRLU"}, {"onMessage": [[{"id": "PFjA3kUE", "inletIndex": 0}]], "id": "cOpO5W1o"}, {"onMessage": [[{"id": "Wxpz8xdG", "inletIndex": 0}]], "id": "SRj0oqC4"}, {"onMessage": [[{"id": "91Q3Vlm5", "inletIndex": 0}]], "id": "04GU2JcG"}, {"onMessage": [[{"id": "GeTZbG9G", "inletIndex": 0}]], "id": "N5Z37uK9"}, {"onMessage": [[{"id": "4Ne3hm7t", "inletIndex": 0}]], "id": "USsAkyex"}, {"onMessage": [[{"id": "KIu4tBtN", "inletIndex": 1}]], "id": "4Ne3hm7t"}, {"onMessage": [[{"id": "j6raFRLU", "inletIndex": 0}, {"id": "SRj0oqC4", "inletIndex": 0}, {"id": "0EtPiUGl", "inletIndex": 0}]], "id": "wdXg9sSu"}, {"onMessage": [[{"id": "SRj0oqC4", "inletIndex": 1}]], "id": "8scupIu8"}, {"onMessage": [[{"id": "8scupIu8", "inletIndex": 0}]], "id": "LFLmCJ1Q"}, {"onMessage": [[{"id": "04GU2JcG", "inletIndex": 0}, {"id": "cOpO5W1o", "inletIndex": 0}, {"id": "PZqNkw5L", "inletIndex": 0}, {"id": "4UTMJI96", "inletIndex": 0}]], "id": "08BLB4hJ"}, {"onMessage": [[{"id": "dUlpqATO", "inletIndex": 0}, {"id": "AHIbzr54", "inletIndex": 0}, {"id": "GUjC9kah", "inletIndex": 0}]], "id": "UUyirtEs"}, {"onMessage": [[{"id": "C4FFxZsY", "inletIndex": 0}, {"id": "NHJrrzJX", "inletIndex": 0}]], "id": "dUlpqATO"}, {"onMessage": [[{"id": "9Nry2y47", "inletIndex": 0}, {"id": "lbPEmnIy", "inletIndex": 0}, {"id": "WM44L5Vk", "inletIndex": 0}, {"id": "9kwKhY4t", "inletIndex": 0}]], "id": "scDLNTaT"}, {"onMessage": [[{"id": "S3p3nSsZ", "inletIndex": 0}]], "id": "5D0S6jWQ"}, {"onMessage": [[{"id": "kp7dpvIA", "inletIndex": 1}]], "id": "O8Q7Bf9l"}, {"onMessage": [[{"id": "iyKOlRMC", "inletIndex": 0}]], "id": "C4FFxZsY"}, {"onMessage": [[{"id": "ejG9TU96", "inletIndex": 0}]], "id": "DsPcXYm5"}, {"onMessage": [[{"id": "vf1pzYkf", "inletIndex": 5}]], "id": "TzLDJGbC"}, {"onMessage": [[{"id": "VYxQxxPq", "inletIndex": 1}]], "id": "uYS7T4kW"}, {"onMessage": [[{"id": "uYS7T4kW", "inletIndex": 0}]], "id": "wuJ2UxHJ"}, {"onMessage": [[{"id": "TzLDJGbC", "inletIndex": 0}]], "id": "S3p3nSsZ"}, {"onMessage": [[{"id": "DsPcXYm5", "inletIndex": 0}, {"id": "O8Q7Bf9l", "inletIndex": 0}, {"id": "y7Nz7ktL", "inletIndex": 0}]], "id": "AJn52BCG"}, {"onMessage": [[{"id": "nuBBhYSo", "inletIndex": 1}]], "id": "KFpYiLtB"}, {"onMessage": [[{"id": "VYxQxxPq", "inletIndex": 0}]], "id": "iyKOlRMC"}, {"onMessage": [[{"id": "uNTMeTgy", "inletIndex": 0}]], "id": "GRJAoClQ"}, {"onMessage": [[{"id": "C4FFxZsY", "inletIndex": 0}]], "id": "lbPEmnIy"}, {"onMessage": [[{"id": "kAFZa1KQ", "inletIndex": 0}]], "id": "QvplIukv"}, {"onMessage": [[{"id": "vf1pzYkf", "inletIndex": 4}]], "id": "uNTMeTgy"}, {"onMessage": [[{"id": "AJn52BCG", "inletIndex": 0}]], "id": "nuBBhYSo"}, {"onMessage": [[{"id": "5D0S6jWQ", "inletIndex": 0}, {"id": "GRJAoClQ", "inletIndex": 0}, {"id": "OJQCiJ3A", "inletIndex": 0}]], "id": "ejG9TU96"}, {"onMessage": [[{"id": "O8Q7Bf9l", "inletIndex": 1}]], "id": "OJQCiJ3A"}, {"onMessage": [[{"id": "KFpYiLtB", "inletIndex": 0}]], "id": "9Nry2y47"}, {"onMessage": [[{"id": "GRJAoClQ", "inletIndex": 1}]], "id": "kAFZa1KQ"}, {"onMessage": [[{"id": "kp7dpvIA", "inletIndex": 0}]], "id": "y7Nz7ktL"}, {"onMessage": [[{"id": "vf1pzYkf", "inletIndex": 1}]], "id": "kp7dpvIA"}, {"onMessage": [[{"id": "OJQCiJ3A", "inletIndex": 1}, {"id": "QvplIukv", "inletIndex": 0}, {"id": "nuBBhYSo", "inletIndex": 0}]], "id": "VYxQxxPq"}, {"onMessage": [[{"id": "YiPqNUkR", "inletIndex": 0}]], "id": "KavicZaW"}, {"onMessage": [[{"id": "fZ6n5LMH", "inletIndex": 1}]], "id": "MnJFiYAX"}, {"onMessage": [[{"id": "aqU6lklK", "inletIndex": 0}]], "id": "ZrMYD9Wk"}, {"onMessage": [[{"id": "SNl7n2og", "inletIndex": 5}]], "id": "aqU6lklK"}, {"onMessage": [[{"id": "hwQ22vSq", "inletIndex": 1}]], "id": "7KkS7int"}, {"onMessage": [[{"id": "SQXWgOR3", "inletIndex": 0}]], "id": "WM44L5Vk"}, {"onMessage": [[{"id": "SNl7n2og", "inletIndex": 1}]], "id": "PvRE7osX"}, {"onMessage": [[{"id": "vENaF9ci", "inletIndex": 0}]], "id": "QVm6HiMY"}, {"onMessage": [[{"id": "YiPqNUkR", "inletIndex": 1}]], "id": "GJdXbLwp"}, {"onMessage": [[{"id": "GJdXbLwp", "inletIndex": 0}]], "id": "qsp8fJ3r"}, {"onMessage": [[{"id": "QVm6HiMY", "inletIndex": 0}, {"id": "fZ6n5LMH", "inletIndex": 0}, {"id": "rPvHqTRV", "inletIndex": 0}]], "id": "rH5kTkdl"}, {"onMessage": [[{"id": "MnJFiYAX", "inletIndex": 1}, {"id": "p7LgnoOd", "inletIndex": 0}, {"id": "YV4hIEni", "inletIndex": 0}]], "id": "YiPqNUkR"}, {"onMessage": [[{"id": "cqU9VHDD", "inletIndex": 0}, {"id": "hwQ22vSq", "inletIndex": 0}, {"id": "MnJFiYAX", "inletIndex": 0}]], "id": "vENaF9ci"}, {"onMessage": [[{"id": "7KkS7int", "inletIndex": 0}]], "id": "p7LgnoOd"}, {"onMessage": [[{"id": "ZrMYD9Wk", "inletIndex": 0}]], "id": "cqU9VHDD"}, {"onMessage": [[{"id": "SNl7n2og", "inletIndex": 4}]], "id": "yXgnLyP6"}, {"onMessage": [[{"id": "yXgnLyP6", "inletIndex": 0}]], "id": "hwQ22vSq"}, {"onMessage": [[{"id": "PvRE7osX", "inletIndex": 0}]], "id": "rPvHqTRV"}, {"onMessage": [[{"id": "rH5kTkdl", "inletIndex": 0}]], "id": "YV4hIEni"}, {"onMessage": [[{"id": "YV4hIEni", "inletIndex": 1}]], "id": "SQXWgOR3"}, {"onMessage": [[{"id": "KavicZaW", "inletIndex": 0}]], "id": "NHJrrzJX"}, {"onMessage": [[{"id": "NHJrrzJX", "inletIndex": 0}]], "id": "9kwKhY4t"}, {"onMessage": [[{"id": "PvRE7osX", "inletIndex": 1}]], "id": "fZ6n5LMH"}, {"onMessage": [[{"id": "f1cOvzsJ", "inletIndex": 0}]], "id": "tjerdydz"}, {"onMessage": [[{"id": "HSDZgDOH", "inletIndex": 1}]], "id": "hsqUZSED"}, {"onMessage": [[{"id": "XoyQF5MG", "inletIndex": 0}]], "id": "36iLMAXw"}, {"onMessage": [[{"id": "EISSvgxs", "inletIndex": 1}]], "id": "XoyQF5MG"}, {"onMessage": [[{"id": "BKBusjyv", "inletIndex": 1}]], "id": "f1cOvzsJ"}, {"onMessage": [[{"id": "yVOwK6mg", "inletIndex": 0}, {"id": "hsqUZSED", "inletIndex": 0}, {"id": "yqP0lt6k", "inletIndex": 0}]], "id": "6ROEk8KH"}, {"onMessage": [[{"id": "HSDZgDOH", "inletIndex": 0}]], "id": "yqP0lt6k"}, {"onMessage": [[{"id": "XmHhEsRF", "inletIndex": 0}]], "id": "3d6iVWIq"}, {"onMessage": [[{"id": "hcyasJ9m", "inletIndex": 4}]], "id": "faOBhJeF"}, {"onMessage": [[{"id": "Bw2GipKX", "inletIndex": 0}]], "id": "1LEJIlTD"}, {"onMessage": [[{"id": "hsqUZSED", "inletIndex": 1}]], "id": "XOa8f9q1"}, {"onMessage": [[{"id": "6ROEk8KH", "inletIndex": 0}]], "id": "zyOD6MwC"}, {"onMessage": [[{"id": "fQYvGIjF", "inletIndex": 0}]], "id": "rGxV73Sc"}, {"onMessage": [[{"id": "EISSvgxs", "inletIndex": 0}]], "id": "hgVc6Xg8"}, {"onMessage": [[{"id": "XOa8f9q1", "inletIndex": 1}, {"id": "tjerdydz", "inletIndex": 0}, {"id": "zyOD6MwC", "inletIndex": 0}]], "id": "EISSvgxs"}, {"onMessage": [[{"id": "hcyasJ9m", "inletIndex": 1}]], "id": "HSDZgDOH"}, {"onMessage": [[{"id": "otLHSXUm", "inletIndex": 0}, {"id": "BKBusjyv", "inletIndex": 0}, {"id": "XOa8f9q1", "inletIndex": 0}]], "id": "lkaKLdaq"}, {"onMessage": [[{"id": "hcyasJ9m", "inletIndex": 5}]], "id": "Bw2GipKX"}, {"onMessage": [[{"id": "faOBhJeF", "inletIndex": 0}]], "id": "BKBusjyv"}, {"onMessage": [[{"id": "hgVc6Xg8", "inletIndex": 0}]], "id": "XmHhEsRF"}, {"onMessage": [[{"id": "zyOD6MwC", "inletIndex": 1}]], "id": "fQYvGIjF"}, {"onMessage": [[{"id": "lkaKLdaq", "inletIndex": 0}]], "id": "yVOwK6mg"}, {"onMessage": [[{"id": "1LEJIlTD", "inletIndex": 0}]], "id": "otLHSXUm"}, {"onMessage": [[{"id": "XmHhEsRF", "inletIndex": 0}, {"id": "XE6cLVzR", "inletIndex": 0}]], "id": "GUjC9kah"}, {"onMessage": [[{"id": "PFjA3kUE", "inletIndex": 0}, {"id": "sV29vKkJ", "inletIndex": 0}]], "id": "AHIbzr54"}], "receivers": {"Q": {"extern": "param", "attributes": {"default": 1.2, "max": 2.0, "min": 0.1}, "hash": "0xF3BA5CD4", "display": "Q", "ids": ["2EnZ9wzD"]}, "centerFrequency_01": {"extern": "param", "attributes": {"default": 130.0, "max": 20000.0, "min": 20.0}, "hash": "0x539436C5", "display": "centerFrequency_01", "ids": ["UUyirtEs"]}, "__hv_init": {"extern": null, "attributes": {}, "hash": "0xCE5CC65B", "display": "__hv_init", "ids": ["mrqNjPCT"]}}}, "tables": {}, "name": {"escaped": "simpleWind", "display": "simpleWind"}, "signal": {"numOutputBuffers": 2, "processOrder": [{"inputBuffers": [], "id": "2PV1A9yt", "outputBuffers": [{"index": 0, "type": "~i>"}]}, {"inputBuffers": [], "id": "XTX8Qhpr", "outputBuffers": [{"index": 1, "type": "~i>"}]}, {"inputBuffers": [{"index": 0, "type": "~i>"}, {"index": 1, "type": "~i>"}], "id": "6fYaVo0h", "outputBuffers": [{"index": 1, "type": "~i>"}]}, {"inputBuffers": [{"index": 1, "type": "~i>"}], "id": "VJntkHtn", "outputBuffers": []}, {"inputBuffers": [{"index": 1, "type": "~i>"}], "id": "NvcNwd1G", "outputBuffers": [{"index": 0, "type": "~f>"}]}, {"inputBuffers": [], "id": "872Wosnb", "outputBuffers": [{"index": 1, "type": "~f>"}]}, {"inputBuffers": [{"index": 0, "type": "~f>"}, {"index": 1, "type": "~f>"}], "id": "AuWmwz9P", "outputBuffers": [{"index": 1, "type": "~f>"}]}, {"inputBuffers": [{"index": 1, "type": "~f>"}], "id": "vf1pzYkf", "outputBuffers": [{"index": 1, "type": "~f>"}]}, {"inputBuffers": [{"index": 1, "type": "~f>"}], "id": "SNl7n2og", "outputBuffers": [{"index": 1, "type": "~f>"}]}, {"inputBuffers": [], "id": "oNuZ6Uxb", "outputBuffers": [{"index": 1, "type": "~i>"}]}, {"inputBuffers": [], "id": "2Q7W9TVG", "outputBuffers": [{"index": 0, "type": "~i>"}]}, {"inputBuffers": [{"index": 1, "type": "~i>"}, {"index": 0, "type": "~i>"}], "id": "yNI5xQ4q", "outputBuffers": [{"index": 0, "type": "~i>"}]}, {"inputBuffers": [{"index": 0, "type": "~i>"}], "id": "xjZqYIZJ", "outputBuffers": []}, {"inputBuffers": [{"index": 0, "type": "~i>"}], "id": "ACVfpaLv", "outputBuffers": [{"index": 0, "type": "~f>"}]}, {"inputBuffers": [], "id": "g5bEs3Mv", "outputBuffers": [{"index": 2, "type": "~f>"}]}, {"inputBuffers": [{"index": 0, "type": "~f>"}, {"index": 2, "type": "~f>"}], "id": "Pwvc7DSk", "outputBuffers": [{"index": 2, "type": "~f>"}]}, {"inputBuffers": [{"index": 2, "type": "~f>"}], "id": "jI3nRZ3I", "outputBuffers": [{"index": 2, "type": "~f>"}]}, {"inputBuffers": [{"index": 2, "type": "~f>"}], "id": "sXHFfO3Q", "outputBuffers": [{"index": 2, "type": "~f>"}]}, {"inputBuffers": [{"index": 1, "type": "~f>"}, {"index": 2, "type": "~f>"}], "id": "aHoPDYIq", "outputBuffers": [{"index": 2, "type": "~f>"}]}, {"inputBuffers": [], "id": "okjr45Xj", "outputBuffers": [{"index": 0, "type": "~i>"}]}, {"inputBuffers": [], "id": "CGvqBOcI", "outputBuffers": [{"index": 1, "type": "~i>"}]}, {"inputBuffers": [{"index": 0, "type": "~i>"}, {"index": 1, "type": "~i>"}], "id": "7XpX7nl1", "outputBuffers": [{"index": 1, "type": "~i>"}]}, {"inputBuffers": [{"index": 1, "type": "~i>"}], "id": "zfd3hl56", "outputBuffers": [{"index": 1, "type": "~f>"}]}, {"inputBuffers": [], "id": "PaAkdPgP", "outputBuffers": [{"index": 0, "type": "~f>"}]}, {"inputBuffers": [{"index": 1, "type": "~f>"}, {"index": 0, "type": "~f>"}], "id": "1uMVma08", "outputBuffers": [{"index": 0, "type": "~f>"}]}, {"inputBuffers": [{"index": 1, "type": "~i>"}], "id": "4LOzo4bx", "outputBuffers": []}, {"inputBuffers": [{"index": 0, "type": "~f>"}], "id": "hcyasJ9m", "outputBuffers": [{"index": 0, "type": "~f>"}]}, {"inputBuffers": [{"index": 0, "type": "~f>"}], "id": "tar7c5jV", "outputBuffers": [{"index": 0, "type": "~f>"}]}, {"inputBuffers": [{"index": 2, "type": "~f>"}, {"index": 0, "type": "~f>"}], "id": "1MYuTpBM", "outputBuffers": [{"index": 0, "type": "~f>"}]}, {"inputBuffers": [], "id": "xVLpZ2lA", "outputBuffers": [{"index": 2, "type": "~f>"}]}, {"inputBuffers": [{"index": 0, "type": "~f>"}, {"index": 2, "type": "~f>"}], "id": "6CVPlw2y", "outputBuffers": [{"index": 2, "type": "~f>"}]}, {"inputBuffers": [{"index": 2, "type": "~f>"}, {"index": 1, "type": "output"}], "id": "Y4VunX5G", "outputBuffers": [{"index": 1, "type": "output"}]}, {"inputBuffers": [{"index": 2, "type": "~f>"}, {"index": 0, "type": "output"}], "id": "SpNQ5AyP", "outputBuffers": [{"index": 0, "type": "output"}]}], "numInputBuffers": 0, "numTemporaryBuffers": {"integer": 2, "float": 3}}, "init": {"order": ["vf1pzYkf", "SNl7n2og", "jI3nRZ3I", "sXHFfO3Q", "hcyasJ9m", "tar7c5jV", "aut8Yt4Y", "Np2A0Hma", "MLl5jsqt", "1oarSilj", "hDGCqg3z", "BX2BM73a", "X3fUcOw4", "VtfBrZPE", "awkwSxvB", "TyPLDmk3", "dHjPAE2h", "khAFsJvr", "duj9Vzsa", "sV29vKkJ", "YgJ9XK9f", "B8xxMvcW", "PZqNkw5L", "aqPsZuvz", "XID8sJpX", "8veCtKn3", "GHgiPdmQ", "bKtq7nSs", "QDP4a1fs", "xawwm4se", "SunTPbc3", "hwFdDnOR", "5sgegJNE", "GWKn0ZtA", "DALXMOTs", "5sUnBs4A", "1gij5Yvz", "RKuXHjLd", "OH7InqxW", "OQc4Eh31", "PN6P17Jp", "3lyQUVNV", "asjgeXP8", "MId9blJb", "BVwUKxZs", "RVgL7XKy", "MAzG1OpX", "UgMUMfMq", "DBzrryKD", "pmAvZCLv", "HyJtdoqi", "cX4wdgmP", "Jj3x8zHW", "r2qEYE1k", "XE6cLVzR", "zxhx5cMP", "WfaAKmnL", "UZ7DgDsX", "KIu4tBtN", "9UaI8X94", "GeTZbG9G", "91Q3Vlm5", "R1lQlkKU", "Wxpz8xdG", "wFc3LBVU", "u19ClEKl", "ufgWJbPN", "0EtPiUGl", "ZDPEjJI5", "PFjA3kUE", "j6raFRLU", "SRj0oqC4", "04GU2JcG", "N5Z37uK9", "wdXg9sSu", "8scupIu8", "08BLB4hJ", "dUlpqATO", "scDLNTaT", "5D0S6jWQ", "O8Q7Bf9l", "C4FFxZsY", "DsPcXYm5", "TzLDJGbC", "S3p3nSsZ", "AJn52BCG", "KFpYiLtB", "iyKOlRMC", "GRJAoClQ", "uNTMeTgy", "nuBBhYSo", "ejG9TU96", "OJQCiJ3A", "9Nry2y47", "kAFZa1KQ", "y7Nz7ktL", "kp7dpvIA", "VYxQxxPq", "KavicZaW", "MnJFiYAX", "ZrMYD9Wk", "aqU6lklK", "7KkS7int", "WM44L5Vk", "PvRE7osX", "QVm6HiMY", "rH5kTkdl", "YiPqNUkR", "vENaF9ci", "cqU9VHDD", "yXgnLyP6", "hwQ22vSq", "rPvHqTRV", "YV4hIEni", "SQXWgOR3", "NHJrrzJX", "fZ6n5LMH", "hsqUZSED", "f1cOvzsJ", "6ROEk8KH", "yqP0lt6k", "faOBhJeF", "1LEJIlTD", "XOa8f9q1", "zyOD6MwC", "rGxV73Sc", "hgVc6Xg8", "EISSvgxs", "HSDZgDOH", "lkaKLdaq", "Bw2GipKX", "BKBusjyv", "XmHhEsRF", "fQYvGIjF", "yVOwK6mg", "otLHSXUm", "GUjC9kah", "AHIbzr54"]}, "objects": {"X3fUcOw4": {"args": {"index": 1.0, "length": 1.0}, "type": "__slice"}, "duj9Vzsa": {"args": {"k": 0.0}, "type": "__mul"}, "ZrMYD9Wk": {"args": {"k": -1.0}, "type": "__mul_k"}, "Y4VunX5G": {"args": {}, "type": "__add~f"}, "xjZqYIZJ": {"args": {"var_id": "VtfBrZPE"}, "type": "__varwrite~i"}, "tjerdydz": {"args": {}, "type": "__cos"}, "RVgL7XKy": {"args": {"k": -1.0}, "type": "__mul_k"}, "TzLDJGbC": {"args": {"k": -1.0}, "type": "__mul_k"}, "9UaI8X94": {"args": {"k": 0.0}, "type": "__add"}, "64WB82kK": {"args": {}, "type": "__floor"}, "08BLB4hJ": {"args": {"k": 0.0}, "type": "__var"}, "f1cOvzsJ": {"args": {"k": 2.0}, "type": "__mul_k"}, "S3p3nSsZ": {"args": {"k": -1.0}, "type": "__mul_k"}, "8veCtKn3": {"args": {"k": 6.28319}, "type": "__mul_k"}, "sXHFfO3Q": {"args": {"fb2": 0.0, "fb1": 0.0, "ff2": 0.0, "ff1": 0.0, "ff0": 1.0}, "type": "__biquad_k~f"}, "vf1pzYkf": {"args": {"fb2": 0.0, "fb1": 0.0, "ff2": 0.0, "ff1": 0.0, "ff0": 1.0}, "type": "__biquad_k~f"}, "GHgiPdmQ": {"args": {"k": 0.0}, "type": "__add"}, "jI3nRZ3I": {"args": {"fb2": 0.0, "fb1": 0.0, "ff2": 0.0, "ff1": 0.0, "ff0": 1.0}, "type": "__biquad_k~f"}, "91Q3Vlm5": {"args": {"k": 0.001}, "type": "__max_k"}, "uNTMeTgy": {"args": {"k": -1.0}, "type": "__mul_k"}, "faOBhJeF": {"args": {"k": -1.0}, "type": "__mul_k"}, "hcyasJ9m": {"args": {"fb2": 0.0, "fb1": 0.0, "ff2": 0.0, "ff1": 0.0, "ff0": 1.0}, "type": "__biquad_k~f"}, "khAFsJvr": {"args": {"index": 1.0, "length": 1.0}, "type": "__slice"}, "Wxpz8xdG": {"args": {"k": -1.0}, "type": "__mul_k"}, "yXgnLyP6": {"args": {"k": -1.0}, "type": "__mul_k"}, "MnJFiYAX": {"args": {"k": 0.0}, "type": "__mul"}, "SQXWgOR3": {"args": {"k": 0.001}, "type": "__max_k"}, "ejG9TU96": {"args": {"k": 1.0}, "type": "__add_k"}, "hwQ22vSq": {"args": {"k": 0.0}, "type": "__mul"}, "wdXg9sSu": {"args": {"k": 1.0}, "type": "__add_k"}, "g5bEs3Mv": {"args": {"k": 4.65661e-10, "step": 0, "reverse": false}, "type": "__var_k~f"}, "1MYuTpBM": {"args": {}, "type": "__add~f"}, "ZDPEjJI5": {"args": {"k": -1.0}, "type": "__mul_k"}, "hwFdDnOR": {"args": {"k": 2.0}, "type": "__mul_k"}, "iyKOlRMC": {"args": {"k": 6.28319}, "type": "__mul_k"}, "HSDZgDOH": {"args": {"k": 0.0}, "type": "__mul"}, "xVLpZ2lA": {"args": {"k": 0.2, "step": 0, "reverse": false}, "type": "__var_k~f"}, "aut8Yt4Y": {"args": {"step": 0, "k": 0, "reverse": false, "name": "x"}, "type": "__var~i"}, "lkaKLdaq": {"args": {"k": 1.0}, "type": "__add_k"}, "GWKn0ZtA": {"args": {"k": 2.0}, "type": "__pow_k"}, "fZ6n5LMH": {"args": {"k": 0.0}, "type": "__add"}, "Pwvc7DSk": {"args": {}, "type": "__mul~f"}, "9kwKhY4t": {"args": {}, "type": "__cast_b"}, "hsqUZSED": {"args": {"k": 0.0}, "type": "__add"}, "zxhx5cMP": {"args": {"k": 0.0}, "type": "__mul"}, "VtfBrZPE": {"args": {"step": 0, "k": 0, "reverse": false, "name": "x"}, "type": "__var~i"}, "rM26PKT8": {"args": {"remote": [], "local": [["$1", "1"]]}, "type": "__message"}, "5D0S6jWQ": {"args": {"k": 2.0}, "type": "__pow_k"}, "PN6P17Jp": {"args": {"k": 1.0}, "type": "__var"}, "iwdWSRnX": {"args": {"remote": [], "local": [["samplerate"]]}, "type": "__message"}, "C4FFxZsY": {"args": {"k": 22050.0}, "type": "__var"}, "PaAkdPgP": {"args": {"k": 4.65661e-10, "step": 0, "reverse": false}, "type": "__var_k~f"}, "OH7InqxW": {"args": {"k": 0.001}, "type": "__max_k"}, "BX2BM73a": {"args": {"k": 8388610.0}, "type": "__mul_k"}, "USsAkyex": {"args": {"remote": [], "local": [["samplerate"]]}, "type": "__message"}, "KIu4tBtN": {"args": {"k": 0.0}, "type": "__div"}, "2PV1A9yt": {"args": {"var_id": "awkwSxvB"}, "type": "__varread~i"}, "OQc4Eh31": {"args": {"k": 2.0}, "type": "__mul_k"}, "RKuXHjLd": {"args": {"k": 0.0}, "type": "__var"}, "Hn7QnS1j": {"args": {}, "type": "__cast_b"}, "dHjPAE2h": {"args": {"range": 2, "seed": -683602384.0}, "type": "__random"}, "6ROEk8KH": {"args": {"k": 1.0}, "type": "__min_k"}, "AJn52BCG": {"args": {"k": 1.0}, "type": "__min_k"}, "YiPqNUkR": {"args": {"k": 0.0}, "type": "__div"}, "sV29vKkJ": {"args": {"k": 22050.0}, "type": "__var"}, "KFpYiLtB": {"args": {"k": 0.001}, "type": "__max_k"}, "bKtq7nSs": {"args": {"k": -1.0}, "type": "__mul_k"}, "GRJAoClQ": {"args": {"k": 0.0}, "type": "__mul"}, "MId9blJb": {"args": {"k": 0.0}, "type": "__add"}, "u19ClEKl": {"args": {"k": 2.0}, "type": "__mul_k"}, "ufgWJbPN": {"args": {"k": -1.0}, "type": "__mul_k"}, "VJntkHtn": {"args": {"var_id": "awkwSxvB"}, "type": "__varwrite~i"}, "1LEJIlTD": {"args": {"k": -1.0}, "type": "__mul_k"}, "hgVc6Xg8": {"args": {"k": 6.28319}, "type": "__mul_k"}, "dkJfqr6y": {"args": {}, "type": "__system"}, "uYS7T4kW": {"args": {}, "type": "__system"}, "SNl7n2og": {"args": {"fb2": 0.0, "fb1": 0.0, "ff2": 0.0, "ff1": 0.0, "ff0": 1.0}, "type": "__biquad_k~f"}, "okjr45Xj": {"args": {"var_id": "aut8Yt4Y"}, "type": "__varread~i"}, "rPvHqTRV": {"args": {"k": 2.0}, "type": "__mul_k"}, "wFc3LBVU": {"args": {"k": 0.0}, "type": "__mul"}, "aqU6lklK": {"args": {"k": -1.0}, "type": "__mul_k"}, "HyJtdoqi": {"args": {"k": 0.0}, "type": "__mul"}, "UUyirtEs": {"args": {"extern": "param", "attributes": {"default": 130.0, "max": 20000.0, "min": 20.0}, "name": "centerFrequency_01"}, "type": "__receive"}, "yVOwK6mg": {"args": {"k": -1.0}, "type": "__mul_k"}, "9Nry2y47": {"args": {"k": 1.0}, "type": "__var"}, "UZ7DgDsX": {"args": {"k": -1.0}, "type": "__mul_k"}, "YgJ9XK9f": {"args": {"k": -1.0}, "type": "__mul_k"}, "Bw2GipKX": {"args": {"k": -1.0}, "type": "__mul_k"}, "VYxQxxPq": {"args": {"k": 0.0}, "type": "__div"}, "EISSvgxs": {"args": {"k": 0.0}, "type": "__div"}, "2Q7W9TVG": {"args": {"k": 16807, "step": 0, "reverse": false}, "type": "__var_k~i"}, "uKqsmIC7": {"args": {"remote": [], "local": [["$1", "1"]]}, "type": "__message"}, "oNuZ6Uxb": {"args": {"var_id": "VtfBrZPE"}, "type": "__varread~i"}, "otLHSXUm": {"args": {"k": 2.0}, "type": "__pow_k"}, "WfaAKmnL": {"args": {"k": 1.0}, "type": "__min_k"}, "KavicZaW": {"args": {"k": 6.28319}, "type": "__mul_k"}, "GUjC9kah": {"args": {"k": 0.0}, "type": "__var"}, "awkwSxvB": {"args": {"step": 0, "k": 0, "reverse": false, "name": "x"}, "type": "__var~i"}, "qsp8fJ3r": {"args": {"remote": [], "local": [["samplerate"]]}, "type": "__message"}, "YV4hIEni": {"args": {"k": 0.0}, "type": "__div"}, "5sgegJNE": {"args": {"k": 0.0}, "type": "__mul"}, "zfd3hl56": {"args": {}, "type": "__cast~if"}, "aqPsZuvz": {"args": {"k": 1.0}, "type": "__add_k"}, "DsPcXYm5": {"args": {"k": -1.0}, "type": "__mul_k"}, "tar7c5jV": {"args": {"fb2": 0.0, "fb1": 0.0, "ff2": 0.0, "ff1": 0.0, "ff0": 1.0}, "type": "__biquad_k~f"}, "3d6iVWIq": {"args": {}, "type": "__cast_b"}, "3lyQUVNV": {"args": {"k": -1.0}, "type": "__mul_k"}, "rH5kTkdl": {"args": {"k": 1.0}, "type": "__min_k"}, "4Ne3hm7t": {"args": {}, "type": "__system"}, "mrqNjPCT": {"args": {"extern": null, "attributes": {}, "name": "__hv_init"}, "type": "__receive"}, "XTX8Qhpr": {"args": {"k": 16807, "step": 0, "reverse": false}, "type": "__var_k~i"}, "6CVPlw2y": {"args": {}, "type": "__mul~f"}, "16KBbHuy": {"args": {"cases": ["seed"]}, "type": "__switchcase"}, "UgMUMfMq": {"args": {"k": -1.0}, "type": "__mul_k"}, "1oarSilj": {"args": {"range": 2, "seed": 2050873210.0}, "type": "__random"}, "lbPEmnIy": {"args": {}, "type": "__cast_b"}, "XOa8f9q1": {"args": {"k": 0.0}, "type": "__mul"}, "DBzrryKD": {"args": {"k": 1.0}, "type": "__add_k"}, "scDLNTaT": {"args": {"k": 0.0}, "type": "__var"}, "QDP4a1fs": {"args": {"k": 1.0}, "type": "__min_k"}, "0EtPiUGl": {"args": {"k": 0.0}, "type": "__mul"}, "MKJjn0Sx": {"args": {"cases": ["seed"]}, "type": "__switchcase"}, "BVwUKxZs": {"args": {"k": 6.28319}, "type": "__mul_k"}, "yqP0lt6k": {"args": {"k": 2.0}, "type": "__mul_k"}, "SunTPbc3": {"args": {"k": 0.001}, "type": "__max_k"}, "Gsokg6Wm": {"args": {}, "type": "__cos"}, "xawwm4se": {"args": {"k": 0.0}, "type": "__div"}, "2EnZ9wzD": {"args": {"extern": "param", "attributes": {"default": 1.2, "max": 2.0, "min": 0.1}, "name": "Q"}, "type": "__receive"}, "AuWmwz9P": {"args": {}, "type": "__mul~f"}, "j6raFRLU": {"args": {"k": 2.0}, "type": "__pow_k"}, "oGrt12K5": {"args": {}, "type": "__cos"}, "kAFZa1KQ": {"args": {"k": 2.0}, "type": "__mul_k"}, "R1lQlkKU": {"args": {"k": 6.28319}, "type": "__mul_k"}, "y7Nz7ktL": {"args": {"k": 2.0}, "type": "__mul_k"}, "yNI5xQ4q": {"args": {"k": 0}, "type": "__mul~i"}, "7KkS7int": {"args": {"k": 2.0}, "type": "__mul_k"}, "zj7mX5Zl": {"args": {}, "type": "__floor"}, "kp7dpvIA": {"args": {"k": 0.0}, "type": "__mul"}, "MLl5jsqt": {"args": {"k": 8388610.0}, "type": "__mul_k"}, "TyPLDmk3": {"args": {"k": 8388610.0}, "type": "__mul_k"}, "pmAvZCLv": {"args": {"k": -1.0}, "type": "__mul_k"}, "ltK4iqoa": {"args": {}, "type": "__system"}, "8scupIu8": {"args": {"k": 2.0}, "type": "__mul_k"}, "O8Q7Bf9l": {"args": {"k": 0.0}, "type": "__add"}, "DALXMOTs": {"args": {"k": 2.0}, "type": "__mul_k"}, "6fYaVo0h": {"args": {"k": 0}, "type": "__mul~i"}, "rGxV73Sc": {"args": {"k": 1.0}, "type": "__var"}, "bnsRVnsp": {"args": {}, "type": "__floor"}, "WM44L5Vk": {"args": {"k": 1.0}, "type": "__var"}, "XID8sJpX": {"args": {"k": 0.0}, "type": "__div"}, "ACVfpaLv": {"args": {}, "type": "__cast~if"}, "XE6cLVzR": {"args": {"k": 22050.0}, "type": "__var"}, "1uMVma08": {"args": {}, "type": "__mul~f"}, "QvplIukv": {"args": {}, "type": "__cos"}, "B8xxMvcW": {"args": {"k": -1.0}, "type": "__mul_k"}, "cX4wdgmP": {"args": {"k": 0.0}, "type": "__div"}, "7H4n2H8V": {"args": {"remote": [], "local": [["samplerate"]]}, "type": "__message"}, "r2qEYE1k": {"args": {"k": 2.0}, "type": "__pow_k"}, "XmHhEsRF": {"args": {"k": 22050.0}, "type": "__var"}, "7XpX7nl1": {"args": {"k": 0}, "type": "__mul~i"}, "PvRE7osX": {"args": {"k": 0.0}, "type": "__mul"}, "ym65bbOa": {"args": {"cases": ["seed"]}, "type": "__switchcase"}, "wuJ2UxHJ": {"args": {"remote": [], "local": [["samplerate"]]}, "type": "__message"}, "34zJbigM": {"args": {"remote": [], "local": [["$1", "1"]]}, "type": "__message"}, "GeTZbG9G": {"args": {"k": 1.0}, "type": "__min_k"}, "aHoPDYIq": {"args": {}, "type": "__add~f"}, "872Wosnb": {"args": {"k": 4.65661e-10, "step": 0, "reverse": false}, "type": "__var_k~f"}, "asjgeXP8": {"args": {"k": 2.0}, "type": "__mul_k"}, "CGvqBOcI": {"args": {"k": 16807, "step": 0, "reverse": false}, "type": "__var_k~i"}, "vENaF9ci": {"args": {"k": 1.0}, "type": "__add_k"}, "p7LgnoOd": {"args": {}, "type": "__cos"}, "BKBusjyv": {"args": {"k": 0.0}, "type": "__mul"}, "OJQCiJ3A": {"args": {"k": 0.0}, "type": "__mul"}, "SpNQ5AyP": {"args": {}, "type": "__add~f"}, "AHIbzr54": {"args": {"k": 0.0}, "type": "__var"}, "zyOD6MwC": {"args": {"k": 0.0}, "type": "__div"}, "nuBBhYSo": {"args": {"k": 0.0}, "type": "__div"}, "hDGCqg3z": {"args": {"range": 2, "seed": 1364900309.0}, "type": "__random"}, "04GU2JcG": {"args": {"k": 1.0}, "type": "__var"}, "dUlpqATO": {"args": {"k": 0.0}, "type": "__var"}, "LFLmCJ1Q": {"args": {}, "type": "__cos"}, "Np2A0Hma": {"args": {"index": 1.0, "length": 1.0}, "type": "__slice"}, "GJdXbLwp": {"args": {}, "type": "__system"}, "cOpO5W1o": {"args": {}, "type": "__cast_b"}, "SRj0oqC4": {"args": {"k": 0.0}, "type": "__mul"}, "PFjA3kUE": {"args": {"k": 22050.0}, "type": "__var"}, "QVm6HiMY": {"args": {"k": -1.0}, "type": "__mul_k"}, "N5Z37uK9": {"args": {"k": 0.0}, "type": "__div"}, "36iLMAXw": {"args": {"remote": [], "local": [["samplerate"]]}, "type": "__message"}, "MAzG1OpX": {"args": {"k": 0.0}, "type": "__mul"}, "NvcNwd1G": {"args": {}, "type": "__cast~if"}, "4UTMJI96": {"args": {}, "type": "__cast_b"}, "NHJrrzJX": {"args": {"k": 22050.0}, "type": "__var"}, "Jj3x8zHW": {"args": {"k": 0.0}, "type": "__div"}, "fQYvGIjF": {"args": {"k": 0.001}, "type": "__max_k"}, "cqU9VHDD": {"args": {"k": 2.0}, "type": "__pow_k"}, "4LOzo4bx": {"args": {"var_id": "aut8Yt4Y"}, "type": "__varwrite~i"}, "PZqNkw5L": {"args": {"k": 1.0}, "type": "__var"}, "5sUnBs4A": {"args": {"k": 0.0}, "type": "__mul"}, "1gij5Yvz": {"args": {"k": -1.0}, "type": "__mul_k"}, "XoyQF5MG": {"args": {}, "type": "__system"}}}